anabrid/redaccess/api/common/__init__.py
anabrid/redaccess/api/common/configs.py
anabrid/redaccess/api/common/kv_keys.py
anabrid/redaccess/api/common/models/__init__.py
anabrid/redaccess/api/common/models/gen/__init__.py
anabrid/redaccess/api/common/models/gen/carrier_config.py
anabrid/redaccess/api/common/models/gen/carrier_status.py
anabrid/redaccess/api/common/models/gen/cluster_config.py
anabrid/redaccess/api/common/models/gen/cluster_config_c.py
anabrid/redaccess/api/common/models/gen/cluster_config_i.py
anabrid/redaccess/api/common/models/gen/cluster_config_m0.py
anabrid/redaccess/api/common/models/gen/cluster_config_m0_elements_inner.py
anabrid/redaccess/api/common/models/gen/cluster_config_u.py
anabrid/redaccess/api/common/models/gen/cluster_status.py
anabrid/redaccess/api/common/models/gen/extra_models.py
anabrid/redaccess/api/common/models/gen/hardware_status.py
anabrid/redaccess/api/common/models/gen/job_request.py
anabrid/redaccess/api/common/models/gen/job_response.py
anabrid/redaccess/api/common/models/gen/job_status.py
anabrid/redaccess/api/common/models/gen/log.py
anabrid/redaccess/api/common/models/gen/log_entry.py
anabrid/redaccess/api/common/models/gen/partition.py
anabrid/redaccess/api/common/models/gen/stats.py
anabrid/redaccess/api/common/models/gen/t_block_config.py
anabrid/redaccess/api/common/models/global_config.py
anabrid_redac_core-0.1.2.dist-info/METADATA
anabrid_redac_core-0.1.2.dist-info/WHEEL
anabrid_redac_core-0.1.2.dist-info/RECORD
